{
  "indexes": [
    {
      "collectionGroup": "friendships",
      "queryScope": "COLLECTION",
      "fields": [
        {
          "fieldPath": "participants",
          "arrayConfig": "CONTAINS"
        },
        {
          "fieldPath": "status",
          "order": "ASCENDING"
        }
      ]
    },
    {
      "collectionGroup": "friendships",
      "queryScope": "COLLECTION",
      "fields": [
        {
          "fieldPath": "participants",
          "arrayConfig": "CONTAINS"
        },
        {
          "fieldPath": "createdAt",
          "order": "DESCENDING"
        }
      ]
    },
    {
      "collectionGroup": "users",
      "queryScope": "COLLECTION",
      "fields": [
        {
          "fieldPath": "last_geohash",
          "order": "ASCENDING"
        },
        {
          "fieldPath": "proximity_status",
          "order": "ASCENDING"
        }
      ]
    },
    {
      "collectionGroup": "gymbro_rooms",
      "queryScope": "COLLECTION",
      "fields": [
        {
          "fieldPath": "status",
          "order": "ASCENDING"
        },
        {
          "fieldPath": "lastActivity",
          "order": "DESCENDING"
        }
      ]
    }
  ],
  "fieldOverrides": [
    {
      "collectionGroup": "friendships",
      "fieldPath": "participants",
      "indexes": [
        {
          "queryScope": "COLLECTION",
          "arrayConfig": "CONTAINS"
        }
      ]
    },
    {
      "collectionGroup": "users",
      "fieldPath": "proximity_id",
      "indexes": [
        {
          "queryScope": "COLLECTION",
          "order": "ASCENDING"
        }
      ]
    },
    {
      "collectionGroup": "users",
      "fieldPath": "profile.email",
      "indexes": [
        {
          "queryScope": "COLLECTION",
          "order": "ASCENDING"
        }
      ]
    },
    {
      "collectionGroup": "users",
      "fieldPath": "email",
      "indexes": [
        {
          "queryScope": "COLLECTION",
          "order": "ASCENDING"
        }
      ]
    }
  ]
}